setup.py
srapi/__init__.py
srapi/client.py
srapi.egg-info/PKG-INFO
srapi.egg-info/SOURCES.txt
srapi.egg-info/dependency_links.txt
srapi.egg-info/top_level.txt