Metadata-Version: 1.0
Name: srapi
Version: 1.0
Summary: Api wrapper for the some random api.
Home-page: UNKNOWN
Author: iWeeti
Author-email: UNKNOWN
License: UNKNOWN
Platform: UNKNOWN
